pysum/__init__.py
pysum/summary_tool.py
pysum-0.1.1.dist-info/METADATA
pysum-0.1.1.dist-info/RECORD
pysum-0.1.1.dist-info/WHEEL
pysum-0.1.1.dist-info/entry_points.txt
pysum-0.1.1.dist-info/top_level.txt
