Metadata-Version: 2.1
Name: pysum
Version: 0.1.1
Summary: Summarize pandas DataFrames
Home-page: https://github.com/soodoku/pysum
Author: Gaurav Sood
Author-email: gsood07@gmail.com
License: MIT
Requires-Dist: pandas
Requires-Dist: pytablewriter
Requires-Dist: tabulate
Provides-Extra: dev
Requires-Dist: check-manifest; extra == 'dev'
Provides-Extra: test
Requires-Dist: coverage; extra == 'test'
